sqlalchemy_profiler-1.0.0.dist-info/METADATA
sqlalchemy_profiler-1.0.0.dist-info/WHEEL
sqlalchemy_profiler-1.0.0.dist-info/licenses/LICENSE
sqlalchemy_profiler/__init__.py
sqlalchemy_profiler/containers.py
sqlalchemy_profiler/ext/__init__.py
sqlalchemy_profiler/ext/fastapi.py
sqlalchemy_profiler/profilers.py
sqlalchemy_profiler/types.py
sqlalchemy_profiler/utils.py
sqlalchemy_profiler-1.0.0.dist-info/RECORD
