Metadata-Version: 2.1
Name: sqlalchemy_profiler
Version: 1.0.0
Summary: SQLAlchemy profiler classes and extentions for other packages.
Author-Email: Dmitriy Lunev <dima.lunev14@gmail.com>
License: MIT
Requires-Python: >=3.11
Requires-Dist: sqlalchemy>=2.0
Requires-Dist: python-dev-utils==7.0.1
Requires-Dist: fastapi; extra == "fastapi"
Provides-Extra: fastapi
